headless_ida/__init__.py
headless_ida/cli.py
headless_ida/client.py
headless_ida/helpers.py
headless_ida/ida_headers.py
headless_ida/ida_script.py
headless_ida/server.py
headless_ida-0.6.7.dist-info/licenses/LICENSE
headless_ida-0.6.7.dist-info/METADATA
headless_ida-0.6.7.dist-info/WHEEL
headless_ida-0.6.7.dist-info/entry_points.txt
headless_ida-0.6.7.dist-info/top_level.txt
headless_ida-0.6.7.dist-info/RECORD
