Metadata-Version: 2.4
Name: headless-ida
Version: 0.6.7
Summary: Headless IDA
Author-email: Han Dai <pypi@han.do>
License: MIT License
Project-URL: homepage, https://github.com/DennyDai/headless-ida
Project-URL: documentation, https://github.com/DennyDai/headless-ida
Project-URL: repository, https://github.com/DennyDai/headless-ida
Keywords: ida,headless,idapro,hexrays
Requires-Python: >=3
License-File: LICENSE
Requires-Dist: rpyc
Dynamic: license-file
